{
  "posts": {
    "payload": [
      {
        "id": 1,
        "title": "json-server",
        "author": "typicode"
      }
    ]
  },
  "courses": [
    {
      "id": "1",
      "title": "Javascript",
      "level": "beginner"
    },
    {
      "id": "2",
      "title": "Angular",
      "level": "beginner"
    },
    {
      "id": "3",
      "title": "Python",
      "level": "beginner"
    },
    {
      "id": "4",
      "title": "c-programming",
      "level": "beginner"
    },
    {
      "id": "5",
      "title": "CI-CD",
      "level": "advanced"
    },
    {
      "id": "6",
      "title": "Docker",
      "level": "advanced"
    },
    {
      "id": "7",
      "title": "Backend",
      "level": "advanced"
    },
    {
      "id": "8",
      "title": "TerraForm",
      "level": "beginner"
    },
    {
      "id": "9",
      "title": "Ansible",
      "level": "advanced"
    },
    {
      "title": "sudhan",
      "level": null,
      "id": "11"
    }
  ],
  "comments": [
    {
      "id": "1",
      "body": "some comment",
      "postId": 1
    }
  ],
  "user": [
    {
      "id": "8a159ab6-24a2-421f-972d-0146f10d1f5a",
      "firstName": "Sudhan",
      "lastName": "Poudel",
      "age": 33,
      "email": "bkspoudel@gmail.com",
      "gender": "male",
      "country": "Nepal"
    },
    {
      "id": "8a159ab6-24a2-421f-972d-0146f10d1l9a",
      "firstName": "John",
      "lastName": "Doe",
      "age": 25,
      "email": "john@example.com",
      "gender": "male",
      "country": "USA"
    },
    {
      "id": "5d69604f-0c22-4068-bd4f-7e550c8c0cb4",
      "firstName": "Sudhan",
      "lastName": "Poudel",
      "age": 22,
      "email": "spodel@yahoo.com",
      "gender": "male",
      "country": "nepal"
    },
    {
      "id": "9ee1c50d-a49e-4585-87db-048a5f63ca5a",
      "firstName": "Suchitra",
      "lastName": "Gyawali Poudel",
      "age": 33,
      "email": "gyawalisuchitra@gmail.com",
      "gender": "male",
      "country": "nepal"
    },
    {
      "id": "0ada37ea-a191-4026-81c4-7aefa2ac192b",
      "firstName": "Suchitra",
      "lastName": "Gyawali Poudel",
      "age": 33,
      "email": "gyawalisuchitra@gmail.com",
      "gender": "male",
      "country": "nepal"
    },
    {
      "firstName": "Kangipur",
      "lastName": null,
      "age": 0,
      "email": null,
      "gender": "male",
      "country": "Nepal",
      "id": "27dc"
    },
    {
      "id": "2ddc",
      "firstName": "Advanced",
      "lastName": "Management",
      "age": 1,
      "email": "gyawalisuchitra@gmail.com",
      "gender": "male",
      "country": "nepal"
    },
    {
      "id": "614fa8d9-0cf3-4750-80b3-f5a09c23bffa",
      "firstName": "Advanced",
      "lastName": "Management",
      "age": 1,
      "email": "gyawalisuchitra@gmail.com",
      "gender": "others",
      "country": "nepal"
    },
    {
      "id": "8ad522c8-fd15-4949-a9f1-59bc3d8bf980",
      "firstName": "Bhuwan Krishna",
      "lastName": "Poudel",
      "age": 81916893,
      "email": "bkspoudel@gmail.com",
      "gender": "male",
      "country": "Denmark"
    },
    {
      "id": "ef4ea494-a8bc-485c-a01d-ad55b2d6ac60",
      "firstName": "Rekha",
      "lastName": "Thapa",
      "age": 3,
      "email": "rekhathapa@gmail.com",
      "gender": "female",
      "country": "nepal"
    }
  ],
  "profile": {
    "name": "typicode"
  }
}